pstats_print2list/__init__.py
pstats_print2list/pstats_print2list.py
pstats_print2list-1.1.9.dist-info/top_level.txt
pstats_print2list-1.1.9.dist-info/METADATA
pstats_print2list-1.1.9.dist-info/DESCRIPTION.rst
pstats_print2list-1.1.9.dist-info/metadata.json
pstats_print2list-1.1.9.dist-info/WHEEL
pstats_print2list-1.1.9.dist-info/RECORD
