Metadata-Version: 2.0
Name: pstats-print2list
Version: 1.1.9
Summary: Add to pstats library of cProfile the feature of get the result in a list with filters, limit and sort.
Home-page: https://github.com/Vauxoo/pstats-print2list
Author: Vauxoo
Author-email: info@vauxoo.com
License: ISCL
Keywords: pstats_print2list
Platform: UNKNOWN
Classifier: Development Status :: 2 - Pre-Alpha
Classifier: Intended Audience :: Developers
Classifier: License :: OSI Approved :: ISC License (ISCL)
Classifier: Natural Language :: English
Classifier: Programming Language :: Python :: 2
Classifier: Programming Language :: Python :: 2.6
Classifier: Programming Language :: Python :: 2.7
